panopti/__init__.py
panopti/config.py
panopti/default_config.toml
panopti/events.py
panopti/run_server.py
panopti/viewer.py
panopti/comms/__init__.py
panopti/comms/websocket.py
panopti/materials/MeshBasicMaterial.py
panopti/materials/MeshDepthMaterial.py
panopti/materials/MeshNormalMaterial.py
panopti/materials/MeshPhysicalMaterial.py
panopti/materials/MeshStandardMaterial.py
panopti/materials/MeshToonMaterial.py
panopti/materials/__init__.py
panopti/materials/base.py
panopti/materials/utils.py
panopti/objects/__init__.py
panopti/objects/animated_mesh.py
panopti/objects/arrows.py
panopti/objects/base.py
panopti/objects/mesh.py
panopti/objects/points.py
panopti/objects/utils.py
panopti/server/__init__.py
panopti/server/app.py
panopti/server/handlers.py
panopti/server/static/dist/index-BksdeqK2.js
panopti/server/static/dist/index-BksdeqK2.js.map
panopti/server/static/dist/index-CHnGN6lb.css
panopti/server/static/dist/index-DJZaVxGs.js
panopti/server/static/dist/index-DJZaVxGs.js.map
panopti/server/static/dist/index.html
panopti/server/static/dist/.vite/manifest.json
panopti/server/static/templates/favicon.ico
panopti/server/static/templates/favicon.png
panopti/server/static/templates/index.html
panopti/ui/__init__.py
panopti/ui/controls.py
panopti/utils/__init__.py
panopti/utils/parse.py
panopti/utils/print_capture.py
panopti/utils/visualize.py
panopti-0.2.0.dist-info/licenses/LICENSE
panopti-0.2.0.dist-info/METADATA
panopti-0.2.0.dist-info/WHEEL
panopti-0.2.0.dist-info/top_level.txt
panopti-0.2.0.dist-info/RECORD
