Metadata-Version: 2.4
Name: panopti
Version: 0.2.0
Summary: Panopti: Interactive 3D visualization in Python.
Author-email: Arman Maesumi <arman.maesumi@gmail.com>
License-Expression: MIT
Project-URL: Homepage, https://github.com/armanmaesumi/panopti
Project-URL: Repository, https://github.com/armanmaesumi/panopti
Project-URL: Documentation, https://armanmaesumi.github.io/panopti/
Keywords: 3D,visualization,geometry,interactive,web
Classifier: Development Status :: 4 - Beta
Classifier: Intended Audience :: Developers
Classifier: Intended Audience :: Science/Research
Classifier: Programming Language :: Python :: 3
Classifier: Programming Language :: Python :: 3.8
Classifier: Programming Language :: Python :: 3.9
Classifier: Programming Language :: Python :: 3.10
Classifier: Programming Language :: Python :: 3.11
Classifier: Programming Language :: Python :: 3.12
Classifier: Topic :: Scientific/Engineering :: Visualization
Classifier: Topic :: Software Development :: Libraries :: Python Modules
Requires-Python: >=3.8
License-File: LICENSE
Requires-Dist: numpy
Requires-Dist: requests
Requires-Dist: flask
Requires-Dist: flask-socketio
Requires-Dist: eventlet
Requires-Dist: python-socketio[client]
Requires-Dist: tomli
Requires-Dist: msgpack
Requires-Dist: trimesh
Dynamic: license-file
